snp_companies/__init__.py
snp_companies/main.py
snp_companies-1.1.dist-info/METADATA
snp_companies-1.1.dist-info/WHEEL
snp_companies-1.1.dist-info/top_level.txt
snp_companies-1.1.dist-info/RECORD
