Metadata-Version: 2.1
Name: snp-companies
Version: 1.1
Summary: Fetches and construct the S&P 500 based on the Wiki page
Home-page: https://github.com/ofrik/snp_companies
Author: Ofri Masad
Author-email: ofrik89@gmail.com
License: UNKNOWN
Platform: UNKNOWN
Classifier: Programming Language :: Python :: 3
Classifier: License :: OSI Approved :: MIT License
Classifier: Operating System :: OS Independent
Requires-Dist: requests (~=2.26.0)
Requires-Dist: beautifulsoup4 (~=4.10.0)
Requires-Dist: numpy (~=1.21.4)
Requires-Dist: pandas (~=1.3.4)
